blogit/__init__.py
blogit/admin.py
blogit/apps.py
blogit/cms_apps.py
blogit/cms_toolbars.py
blogit/feeds.py
blogit/managers.py
blogit/models.py
blogit/settings.py
blogit/sitemaps.py
blogit/urls.py
blogit/utils.py
blogit/views.py
blogit/migrations/0001_initial.py
blogit/migrations/0002_remove_null_from_manytomany.py
blogit/migrations/__init__.py
blogit/static/blogit/css/post_admin.css
blogit/static/blogit/js/post_admin.js
blogit/templates/blogit/base.html
blogit/templates/blogit/category_detail.html
blogit/templates/blogit/category_list.html
blogit/templates/blogit/post_detail.html
blogit/templates/blogit/post_list.html
blogit/templates/blogit/tag_detail.html
blogit/templates/blogit/tag_list.html
blogit/templatetags/__init__.py
blogit/templatetags/blogit_tags.py
djangocms_blogit-0.4.9.dist-info/DESCRIPTION.rst
djangocms_blogit-0.4.9.dist-info/LICENSE.txt
djangocms_blogit-0.4.9.dist-info/METADATA
djangocms_blogit-0.4.9.dist-info/RECORD
djangocms_blogit-0.4.9.dist-info/WHEEL
djangocms_blogit-0.4.9.dist-info/metadata.json
djangocms_blogit-0.4.9.dist-info/top_level.txt
