Metadata-Version: 2.0
Name: djangocms-blogit
Version: 0.4.9
Summary: A simple djangoCMS blog app.
Home-page: https://github.com/dinoperovic/djangocms-blogit
Author: Dino Perovic
Author-email: dino.perovic@gmail.com
License: BSD License
Platform: OS Independent
Classifier: Environment :: Web Environment
Classifier: Framework :: Django
Classifier: Intended Audience :: Developers
Classifier: License :: OSI Approved :: BSD License
Classifier: Operating System :: OS Independent
Classifier: Programming Language :: Python :: 2.7
Classifier: Programming Language :: Python :: 3.4
Classifier: Programming Language :: Python :: 3.5
Requires-Dist: django-cms (>=3.3)
Requires-Dist: django-filer (>=1.2)
Requires-Dist: django-mptt (>=0.8.6)
Requires-Dist: django-parler (>=1.6.5)
